data_structures/__init__.py
data_structures/array.py
data_structures/binary_tree.py
data_structures/circular_linked_list.py
data_structures/doubly_linked_list.py
data_structures/graph.py
data_structures/linked_list.py
data_structures/queue.py
data_structures/stack.py
data_structures/tree.py
danielle_data_structures_python-0.1.0.dist-info/METADATA
danielle_data_structures_python-0.1.0.dist-info/WHEEL
danielle_data_structures_python-0.1.0.dist-info/top_level.txt
danielle_data_structures_python-0.1.0.dist-info/RECORD
