Metadata-Version: 2.4
Name: danielle_data_structures_python
Version: 0.1.0
Summary: A Python package to manage basic data structures like arrays, stacks, queues, and lists.
Home-page: https://github.com/dany237/data-structures-python
Author: Danielle Kapsa
Classifier: Programming Language :: Python :: 3
Classifier: Operating System :: OS Independent
Requires-Python: >=3.6
Dynamic: author
Dynamic: classifier
Dynamic: description
Dynamic: description-content-type
Dynamic: home-page
Dynamic: requires-python
Dynamic: summary
